flask_email_module/__init__.py
flask_email_module/main.py
flask_email_module-0.1.0.dist-info/METADATA
flask_email_module-0.1.0.dist-info/WHEEL
flask_email_module-0.1.0.dist-info/top_level.txt
flask_email_module-0.1.0.dist-info/RECORD
