Metadata-Version: 2.4
Name: flask_email_module
Version: 0.1.0
Summary: A Flask module that captures login form data and sends it via email.
Home-page: https://github.com/Baskar245/flask_email_module
Author: Baskar
Author-email: newtonbaskar04@gmail.com
Classifier: Programming Language :: Python :: 3
Classifier: Framework :: Flask
Classifier: Operating System :: OS Independent
Requires-Python: >=3.6
Requires-Dist: Flask
Dynamic: author
Dynamic: author-email
Dynamic: classifier
Dynamic: description
Dynamic: description-content-type
Dynamic: home-page
Dynamic: requires-dist
Dynamic: requires-python
Dynamic: summary
